Workbook
Name DescriptionsList: 'Material Items'!$A$2:INDEX('Material Items'!$A:$A,COUNTA('Material Items'!$A:$A))

Sheet Quote
E1: Divergent Solutions LLC | H1: Scottsboro, AL 35769
E2: 256-599-0469 | F2: Seth Talley
E3: 256-597-6998 | F3: Brent Wilbanks
A6: QUOTE
A9: Quote Number | C9: 1 | E9: Customer Name | F9: Jamie Darwin
A10: Quote Date | B10: =TODAY() -> 46127 | C10: =TODAY() -> 46127 | E10: Address | F10: 85 Woodland Park Dr
A11: Valid Through | B11: =IF(B10="","",B10+Settings!$B$3) -> 46157 | C11: =IF(C10="","",C10+[1]Settings!$B$3) -> 46157 | E11: Phone | F11: 2566050544
A12: Price Tier | B12: Residential | C12: Residential
A14: Description | H14: Qty | I14: Unit Price | J14: Line Total | K14: Mat. Unit Cost | L14: Mat. Line Cost
A15: 6" Seamless Guttercoil | H15: 252 | I15: =IF($A15="","",IFERROR(INDEX('Material Items'!$B:$D,MATCH($A15,'Material Items'!$A:$A,0),MATCH($B$12,'Material Items'!$B$1:$D$1,0)),"")) -> 7 | J15: =IF(OR($A15="",$H15="",$I15=""),"",H15*I15) -> 1764 | K15: =IF($A15="","",IFERROR(INDEX('Material Items'!$B:$B,MATCH($A15,'Material Items'!$A:$A,0)),"")) -> 2.09 | L15: =IF(OR($A15="",$H15="",$K15=""),"",H15*K15) -> 526.68
A16: Down Spout | H16: 7 | I16: =IF($A16="","",IFERROR(INDEX('Material Items'!$B:$D,MATCH($A16,'Material Items'!$A:$A,0),MATCH($B$12,'Material Items'!$B$1:$D$1,0)),"")) -> 70 | J16: =IF(OR($A16="",$H16="",$I16=""),"",H16*I16) -> 490 | K16: =IF($A16="","",IFERROR(INDEX('Material Items'!$B:$B,MATCH($A16,'Material Items'!$A:$A,0)),"")) -> 15.7 | L16: =IF(OR($A16="",$H16="",$K16=""),"",H16*K16) -> 109.9
A17: A Elbow | H17: 21 | I17: =IF($A17="","",IFERROR(INDEX('Material Items'!$B:$D,MATCH($A17,'Material Items'!$A:$A,0),MATCH($B$12,'Material Items'!$B$1:$D$1,0)),"")) -> 7 | J17: =IF(OR($A17="",$H17="",$I17=""),"",H17*I17) -> 147 | K17: =IF($A17="","",IFERROR(INDEX('Material Items'!$B:$B,MATCH($A17,'Material Items'!$A:$A,0)),"")) -> 2.04 | L17: =IF(OR($A17="",$H17="",$K17=""),"",H17*K17) -> 42.84
A18: Inside Miter | H18: 2 | I18: =IF($A18="","",IFERROR(INDEX('Material Items'!$B:$D,MATCH($A18,'Material Items'!$A:$A,0),MATCH($B$12,'Material Items'!$B$1:$D$1,0)),"")) -> 32 | J18: =IF(OR($A18="",$H18="",$I18=""),"",H18*I18) -> 64 | K18: =IF($A18="","",IFERROR(INDEX('Material Items'!$B:$B,MATCH($A18,'Material Items'!$A:$A,0)),"")) -> 20 | L18: =IF(OR($A18="",$H18="",$K18=""),"",H18*K18) -> 40
A19: 4 crimp offsets | H19: 4 | I19: =IF($A19="","",IFERROR(INDEX('Material Items'!$B:$D,MATCH($A19,'Material Items'!$A:$A,0),MATCH($B$12,'Material Items'!$B$1:$D$1,0)),"")) -> 7 | J19: =IF(OR($A19="",$H19="",$I19=""),"",H19*I19) -> 28 | K19: =IF($A19="","",IFERROR(INDEX('Material Items'!$B:$B,MATCH($A19,'Material Items'!$A:$A,0)),"")) -> 2 | L19: =IF(OR($A19="",$H19="",$K19=""),"",H19*K19) -> 8
A20: 6" End Caps Left | H20: 3 | I20: =IF($A20="","",IFERROR(INDEX('Material Items'!$B:$D,MATCH($A20,'Material Items'!$A:$A,0),MATCH($B$12,'Material Items'!$B$1:$D$1,0)),"")) -> 0 | J20: =IF(OR($A20="",$H20="",$I20=""),"",H20*I20) -> 0 | K20: =IF($A20="","",IFERROR(INDEX('Material Items'!$B:$B,MATCH($A20,'Material Items'!$A:$A,0)),"")) -> 1.84 | L20: =IF(OR($A20="",$H20="",$K20=""),"",H20*K20) -> 5.52
A21: 6" End Caps Right | H21: 3 | I21: =IF($A21="","",IFERROR(INDEX('Material Items'!$B:$D,MATCH($A21,'Material Items'!$A:$A,0),MATCH($B$12,'Material Items'!$B$1:$D$1,0)),"")) -> 0 | J21: =IF(OR($A21="",$H21="",$I21=""),"",H21*I21) -> 0 | K21: =IF($A21="","",IFERROR(INDEX('Material Items'!$B:$B,MATCH($A21,'Material Items'!$A:$A,0)),"")) -> 1.84 | L21: =IF(OR($A21="",$H21="",$K21=""),"",H21*K21) -> 5.52
A22: Straps | H22: 14 | I22: =IF($A22="","",IFERROR(INDEX('Material Items'!$B:$D,MATCH($A22,'Material Items'!$A:$A,0),MATCH($B$12,'Material Items'!$B$1:$D$1,0)),"")) -> 2 | J22: =IF(OR($A22="",$H22="",$I22=""),"",H22*I22) -> 28 | K22: =IF($A22="","",IFERROR(INDEX('Material Items'!$B:$B,MATCH($A22,'Material Items'!$A:$A,0)),"")) -> 2 | L22: =IF(OR($A22="",$H22="",$K22=""),"",H22*K22) -> 28
A23: Clips/100 | H23: 84 | I23: =IF($A23="","",IFERROR(INDEX('Material Items'!$B:$D,MATCH($A23,'Material Items'!$A:$A,0),MATCH($B$12,'Material Items'!$B$1:$D$1,0)),"")) -> 0.55 | J23: =IF(OR($A23="",$H23="",$I23=""),"",H23*I23) -> 46.2 | K23: =IF($A23="","",IFERROR(INDEX('Material Items'!$B:$B,MATCH($A23,'Material Items'!$A:$A,0)),"")) -> 0.55 | L23: =IF(OR($A23="",$H23="",$K23=""),"",H23*K23) -> 46.2
A24: Outside Miters | H24: 8 | I24: =IF($A24="","",IFERROR(INDEX('Material Items'!$B:$D,MATCH($A24,'Material Items'!$A:$A,0),MATCH($B$12,'Material Items'!$B$1:$D$1,0)),"")) -> 32 | J24: =IF(OR($A24="",$H24="",$I24=""),"",H24*I24) -> 256 | K24: =IF($A24="","",IFERROR(INDEX('Material Items'!$B:$B,MATCH($A24,'Material Items'!$A:$A,0)),"")) -> 20 | L24: =IF(OR($A24="",$H24="",$K24=""),"",H24*K24) -> 160
I25: =IF($A25="","",IFERROR(INDEX('Material Items'!$B:$D,MATCH($A25,'Material Items'!$A:$A,0),MATCH($B$12,'Material Items'!$B$1:$D$1,0)),"")) | J25: =IF(OR($A25="",$H25="",$I25=""),"",H25*I25) | K25: =IF($A25="","",IFERROR(INDEX('Material Items'!$B:$B,MATCH($A25,'Material Items'!$A:$A,0)),"")) | L25: =IF(OR($A25="",$H25="",$K25=""),"",H25*K25)
I26: =IF($A26="","",IFERROR(INDEX('Material Items'!$B:$D,MATCH($A26,'Material Items'!$A:$A,0),MATCH($B$12,'Material Items'!$B$1:$D$1,0)),"")) | J26: =IF(OR($A26="",$H26="",$I26=""),"",H26*I26) | K26: =IF($A26="","",IFERROR(INDEX('Material Items'!$B:$B,MATCH($A26,'Material Items'!$A:$A,0)),"")) | L26: =IF(OR($A26="",$H26="",$K26=""),"",H26*K26)
H28: Total | J28: =IF(COUNT(J15:J26)=0,"",SUM(J15:J26)) -> 2823.2 | L28: =IF(COUNT(L15:L26)=0,"",SUM(L15:L26)) -> 972.66
A29: Color | C29: Black

Sheet Material Items
A1: Description | B1: Item Price | C1: Contractor | D1: Residential
A2: 6" Seamless Guttercoil | B2: 2.09 | C2: 6.5 | D2: 7
A3: Down Spout | B3: 15.7 | C3: 65 | D3: 70
A4: A Elbow | B4: 2.04 | C4: 6.5 | D4: 7
A5: B Elbow | B5: 2.04 | C5: 6.5 | D5: 7
A6: 2 crimp offsets | B6: 2 | C6: 6.5 | D6: 7
A7: 4 crimp offsets | B7: 2 | C7: 6.5 | D7: 7
A8: 6" End Caps Left | B8: 1.84 | C8: 0 | D8: 0
A9: 6" End Caps Right | B9: 1.84 | C9: 0 | D9: 0
A10: Clips/100 | B10: 0.55 | C10: 0.55 | D10: 0.55
A11: Inside Miter | B11: 20 | C11: 32 | D11: 32
A12: Outside Miters | B12: 20 | C12: 32 | D12: 32
A13: Strip Miters | B13: 20 | C13: 32 | D13: 32
... A16: Straps | B16: 2 | C16: 2 | D16: 2

Sheet Invoice
E1: Divergent Solutions LLC | H1: Scottsboro, AL 35769
E2: 256-599-0469 | F2: Seth Talley
E3: 256-597-6998 | F3: Brent Wilbanks
A6: INVOICE
A9: Invoice Number | B9: =IF(Quote!B9="","",Quote!B9&"-"&Settings!$B$4) | C9: House 20 | E9: Customer Name | F9: =IF(Quote!F9="","",Quote!F9) -> Jamie Darwin
A10: Invoice Date | B10: =TODAY() -> 46127 | C10: 46118 | E10: Address | F10: =IF(Quote!F10="","",Quote!F10) -> 85 Woodland Park Dr | G10: =IF(Quote!G10="","",Quote!G10) | H10: =IF(Quote!H10="","",Quote!H10)
A11: Due Date | B11: =IF(B10="","",B10+Settings!$B$3) -> 46157 | E11: Phone | F11: =IF(Quote!F11="","",Quote!F11) -> 2566050544 | G11: =IF(Quote!G11="","",Quote!G11) | H11: =IF(Quote!H11="","",Quote!H11)
A12: Payment Terms | B12: =Settings!$B$3&" days" -> 30 days | E12: Source Quote | F12: =IF(Quote!B9="","",Quote!B9)
A14: Description | C14: Color | H14: Qty | I14: Unit Price | J14: Line Total
A15: =IF(Quote!A15="","",Quote!A15) -> 6" Seamless Guttercoil | C15: Black | H15: =IF(Quote!H15="","",Quote!H15) -> 252 | I15: =IF(Quote!I15="","",Quote!I15) -> 7 | J15: =IF(OR($A15="",$H15="",$I15=""),"",H15*I15) -> 1764
A16: =IF(Quote!A16="","",Quote!A16) -> Down Spout | H16: =IF(Quote!H16="","",Quote!H16) -> 7 | I16: =IF(Quote!I16="","",Quote!I16) -> 70 | J16: =IF(OR($A16="",$H16="",$I16=""),"",H16*I16) -> 490
A17: =IF(Quote!A17="","",Quote!A17) -> A Elbow | H17: =IF(Quote!H17="","",Quote!H17) -> 21 | I17: =IF(Quote!I17="","",Quote!I17) -> 7 | J17: =IF(OR($A17="",$H17="",$I17=""),"",H17*I17) -> 147
A18: =IF(Quote!A18="","",Quote!A18) -> Inside Miter | H18: =IF(Quote!H18="","",Quote!H18) -> 2 | I18: =IF(Quote!I18="","",Quote!I18) -> 32 | J18: =IF(OR($A18="",$H18="",$I18=""),"",H18*I18) -> 64
A19: =IF(Quote!A19="","",Quote!A19) -> 4 crimp offsets | H19: =IF(Quote!H19="","",Quote!H19) -> 4 | I19: =IF(Quote!I19="","",Quote!I19) -> 7 | J19: =IF(OR($A19="",$H19="",$I19=""),"",H19*I19) -> 28
A20: =IF(Quote!A20="","",Quote!A20) -> 6" End Caps Left | H20: =IF(Quote!H20="","",Quote!H20) -> 3 | I20: =IF(Quote!I20="","",Quote!I20) -> 0 | J20: =IF(OR($A20="",$H20="",$I20=""),"",H20*I20) -> 0
A21: =IF(Quote!A21="","",Quote!A21) -> 6" End Caps Right | H21: =IF(Quote!H21="","",Quote!H21) -> 3 | I21: =IF(Quote!I21="","",Quote!I21) -> 0 | J21: =IF(OR($A21="",$H21="",$I21=""),"",H21*I21) -> 0
A22: =IF(Quote!A22="","",Quote!A22) -> Straps | H22: =IF(Quote!H22="","",Quote!H22) -> 14 | I22: =IF(Quote!I22="","",Quote!I22) -> 2 | J22: =IF(OR($A22="",$H22="",$I22=""),"",H22*I22) -> 28
A23: =IF(Quote!A23="","",Quote!A23) -> Clips/100 | H23: =IF(Quote!H23="","",Quote!H23) -> 84 | I23: =IF(Quote!I23="","",Quote!I23) -> 0.55 | J23: =IF(OR($A23="",$H23="",$I23=""),"",H23*I23) -> 46.2
A24: =IF(Quote!A24="","",Quote!A24) -> Outside Miters | H24: =IF(Quote!H24="","",Quote!H24) -> 8 | I24: =IF(Quote!I24="","",Quote!I24) -> 32 | J24: =IF(OR($A24="",$H24="",$I24=""),"",H24*I24) -> 256
A25: =IF(Quote!A25="","",Quote!A25) | H25: =IF(Quote!H25="","",Quote!H25) | I25: =IF(Quote!I25="","",Quote!I25) | J25: =IF(OR($A25="",$H25="",$I25=""),"",H25*I25)
A26: =IF(Quote!A26="","",Quote!A26) | H26: =IF(Quote!H26="","",Quote!H26) | I26: =IF(Quote!I26="","",Quote!I26) | J26: =IF(OR($A26="",$H26="",$I26=""),"",H26*I26)
H28: Total | J28: =IF(COUNT(J15:J26)=0,"",SUM(J15:J26)) -> 2823.2

Sheet Settings
A1: Settings
A3: Invoice Due (days) | B3: 30
A4: Invoice Suffix | B4: INV
A6: How pricing works
A7: Choose the price tier on the Quote tab (B12) to switch between Item Price, Contractor, or Residential pricing.

Sheet How To
A1: How to use this workbook
A3: 1. Fill out the Quote tab: quote number, customer info, material descriptions, quantities, and the price tier in B12.
A4: 2. Add new materials on the Material Items tab in the next blank row. The Quote tab dropdown and pricing formulas will pick them up automatically.
A5: 3. If you want a frozen invoice record, duplicate the Invoice tab in Excel and paste values over the formulas.
A6: 4. Change invoice terms or invoice suffix on the Settings tab.
A7: 5. The Net Profits tab shows the current invoice total, internal material cost, and net profit. Copy the current row there and paste values into the archive table to keep each finished invoice in your history.

Sheet Net Profits
A1: Current Invoice Profit Snapshot
A2: Invoice Number | B2: Date | C2: Customer Name | D2: Phone Number | E2: Invoice Total | F2: Material Cost | G2: Net Profit | H2: How to use
A3: =IF(Invoice!B9="","",Invoice!B9) | B3: =IF(Invoice!B10="","",Invoice!B10) -> 46127 | C3: =IF(Invoice!F9="","",Invoice!F9) -> Jamie Darwin | D3: =IF(Invoice!F11="","",Invoice!F11) -> 2566050544 | E3: =IF(Invoice!J28="","",Invoice!J28) -> 2823.2 | F3: =IF(Quote!L28="","",Quote!L28) -> 972.66 | G3: =IF(OR(E3="",F3=""),"",E3-F3) -> 1850.54 | H3: This row auto-fills from the current Invoice tab. To keep a permanent history, copy A3:G3 and paste values into the archive table below before starting the next invoice.
A5: Invoice Archive
A6: Invoice Number | B6: Date | C6: Customer Name | D6: Phone Number | E6: Invoice Total | F6: Material Cost | G6: Net Profit
A7: House 20 | B7: 46127 | C7: Brittney Lambert | E7: 1244 | F7: 461.18 | G7: 782.82
A8: House 40 | B8: 46127 | C8: Brittney Lambert | E8: 1028 | F8: 362.59 | G8: 665.41
A9: House 60 | B9: 46127 | C9: Brittney Lambert | E9: 2112 | F9: 737.39 | G9: 1374.61
A10: House 80 | B10: 46127 | C10: Brittney Lambert | E10: 1324 | F10: 486.59 | G10: 837.41
A11: House 100 | B11: 46127 | C11: Brittney Lambert | E11: 1366 | F11: 487.75 | G11: 878.25
